{"fixture":{"gameweek":{"id":1307,"gameweek":1},"kickoff":{"completeness":3,"millis":1470768300000,"label":"Tue 9 Aug 2016, 19:45 BST","gmtOffset":1.0},"provisionalKickoff":{"completeness":0},"teams":[{"team":{"name":"Sheffield United","club":{"name":"Sheffield United","abbr":"SHU","id":18},"teamType":"FIRST","shortName":"Sheff Utd","id":18},"score":1},{"team":{"name":"Crewe Alexandra","club":{"name":"Crewe Alexandra","abbr":"CRE","id":143},"teamType":"FIRST","shortName":"Crewe","id":143},"score":2}],"replay":false,"ground":{"name":"Bramall Lane","city":"Sheffield","id":206},"neutralGround":false,"status":"C","phase":"F","outcome":"D","attendance":8305,"clock":{"secs":7320,"label":"120 +2\u002700"},"fixtureType":"CUP","extraTime":true,"shootout":false,"aetWinnerId":143,"id":14449},"events":{"pageInfo":{"page":0,"numPages":1,"pageSize":1000,"numEntries":107},"content":[{"id":103189,"time":{"secs":7281,"label":"120 +2"},"type":"end 4","text":"Second Half Extra Time ends, Sheffield United 1, Crewe Alexandra 2."},{"id":103191,"time":{"secs":7275,"label":"120 +2"},"type":"attempt saved","text":"Attempt saved. Chris Basham (Sheffield United) right footed shot from the centre of the box is saved in the centre of the goal.","playerIds":[3581]},{"id":103187,"time":{"secs":7256,"label":"120 +1"},"type":"corner","text":"Corner,  Sheffield United. Conceded by Alex Kiwomya.","playerIds":[10971]},{"id":103186,"time":{"secs":7160,"label":"120"},"type":"free kick won","text":"George Cooper (Crewe Alexandra) wins a free kick in the attacking half.","playerIds":[10689]},{"id":103192,"time":{"secs":7160,"label":"120"},"type":"free kick lost","text":"Foul by John Fleck (Sheffield United).","playerIds":[8444]},{"id":103188,"time":{"secs":6989,"label":"117"},"type":"free kick won","text":"Mark Duffy (Sheffield United) wins a free kick in the defensive half.","playerIds":[8605]},{"id":103197,"time":{"secs":6989,"label":"117"},"type":"free kick lost","text":"Foul by Chris Dagnall (Crewe Alexandra).","playerIds":[9000]},{"id":103193,"time":{"secs":6908,"label":"116"},"type":"free kick lost","text":"Foul by Ryan Lowe (Crewe Alexandra).","playerIds":[9905]},{"id":103194,"time":{"secs":6908,"label":"116"},"type":"free kick won","text":"James Wilson (Sheffield United) wins a free kick in the attacking half.","playerIds":[9298]},{"id":103195,"time":{"secs":6863,"label":"115"},"type":"free kick lost","text":"Foul by Chris Basham (Sheffield United).","playerIds":[3581]},{"id":103196,"time":{"secs":6863,"label":"115"},"type":"free kick won","text":"George Cooper (Crewe Alexandra) wins a free kick in the attacking half.","playerIds":[10689]},{"id":103183,"time":{"secs":6851,"label":"115"},"type":"post","text":"Mark Duffy (Sheffield United) hits the bar with a right footed shot from outside the box.","playerIds":[8605]},{"id":103184,"time":{"secs":6764,"label":"113"},"type":"free kick lost","text":"Foul by Dominic Calvert-Lewin (Sheffield United).","playerIds":[9576]},{"id":103185,"time":{"secs":6764,"label":"113"},"type":"free kick won","text":"George Ray (Crewe Alexandra) wins a free kick in the attacking half.","playerIds":[8482]},{"id":102975,"time":{"secs":6548,"label":"110"},"type":"miss","text":"Attempt missed. Chris Basham (Sheffield United) right footed shot from outside the box is too high.","playerIds":[3581]},{"id":102958,"time":{"secs":6438,"label":"108"},"type":"free kick won","text":"Zoumana Bakayogo (Crewe Alexandra) wins a free kick in the attacking half.","playerIds":[8969]},{"id":102977,"time":{"secs":6438,"label":"108"},"type":"free kick lost","text":"Foul by Marc McNulty (Sheffield United).","playerIds":[10903]},{"id":102971,"time":{"secs":6411,"label":"107"},"type":"post","text":"John Fleck (Sheffield United) hits the bar with a left footed shot from outside the box.","playerIds":[8444]},{"id":102976,"time":{"secs":6300,"label":"106"},"type":"start","text":"Second Half Extra Time begins Sheffield United 1, Crewe Alexandra 2."},{"id":102974,"time":{"secs":6307,"label":"105 +1"},"type":"end 3","text":"First Half Extra Time ends, Sheffield United 1, Crewe Alexandra 2."},{"id":102758,"time":{"secs":6116,"label":"102"},"type":"miss","text":"Attempt missed. Ryan Lowe (Crewe Alexandra) right footed shot from outside the box misses to the right.","playerIds":[9905]},{"id":102763,"time":{"secs":5965,"label":"100"},"type":"goal","text":"Goal!  Sheffield United 1, Crewe Alexandra 2. Ryan Lowe (Crewe Alexandra) right footed shot from the centre of the box to the bottom right corner. Assisted by Ben Nugent following a set piece situation.","playerIds":[9905,9348]},{"id":102704,"time":{"secs":5793,"label":"97"},"type":"corner","text":"Corner,  Sheffield United. Conceded by Alex Kiwomya.","playerIds":[10971]},{"id":102648,"time":{"secs":5780,"label":"97"},"type":"attempt saved","text":"Attempt saved. John Brayford (Sheffield United) right footed shot from outside the box is saved in the bottom right corner.","playerIds":[4729]},{"id":102571,"time":{"secs":5474,"label":"92"},"type":"attempt saved","text":"Attempt saved. Mark Duffy (Sheffield United) right footed shot from outside the box is saved in the centre of the goal.","playerIds":[8605]},{"id":102572,"time":{"secs":5444,"label":"91"},"type":"corner","text":"Corner,  Crewe Alexandra. Conceded by James Wilson.","playerIds":[9298]},{"id":102573,"time":{"secs":5431,"label":"91"},"type":"corner","text":"Corner,  Crewe Alexandra. Conceded by Chris Basham.","playerIds":[3581]},{"id":102556,"time":{"secs":5400,"label":"91"},"type":"start","text":"First Half Extra Time begins Sheffield United 1, Crewe Alexandra 1."},{"id":103190,"time":{"secs":0,"label":"01"},"type":"end 14","text":"Match ends, Sheffield United 1, Crewe Alexandra 2."},{"id":102393,"time":{"secs":5646,"label":"90 +5"},"type":"end 2","text":"Second Half ends, Sheffield United 1, Crewe Alexandra 1."},{"id":102389,"time":{"secs":5484,"label":"90 +2"},"type":"free kick won","text":"Ben Nugent (Crewe Alexandra) wins a free kick in the defensive half.","playerIds":[9348]},{"id":102390,"time":{"secs":5484,"label":"90 +2"},"type":"free kick lost","text":"Foul by Chris Basham (Sheffield United).","playerIds":[3581]},{"id":102396,"time":{"secs":5406,"label":"90 +1"},"type":"corner","text":"Corner,  Sheffield United. Conceded by Perry Ng.","playerIds":[10687]},{"id":102394,"time":{"secs":5336,"label":"89"},"type":"goal","text":"Goal!  Sheffield United 1, Crewe Alexandra 1. Ryan Lowe (Crewe Alexandra) right footed shot from the centre of the box to the bottom right corner following a corner.","playerIds":[9905]},{"id":102386,"time":{"secs":5314,"label":"89"},"type":"corner","text":"Corner,  Crewe Alexandra. Conceded by George Long.","playerIds":[9562]},{"id":102387,"time":{"secs":5306,"label":"89"},"type":"attempt saved","text":"Attempt saved. Ryan Lowe (Crewe Alexandra) right footed shot from outside the box is saved in the bottom right corner.","playerIds":[9905]},{"id":102395,"time":{"secs":5248,"label":"88"},"type":"miss","text":"Attempt missed. Dominic Calvert-Lewin (Sheffield United) right footed shot from the centre of the box misses to the left.","playerIds":[9576]},{"id":102388,"time":{"secs":5160,"label":"87"},"type":"free kick won","text":"Perry Ng (Crewe Alexandra) wins a free kick in the attacking half.","playerIds":[10687]},{"id":102392,"time":{"secs":5159,"label":"86"},"type":"free kick lost","text":"Foul by Dominic Calvert-Lewin (Sheffield United).","playerIds":[9576]},{"id":102391,"time":{"secs":5043,"label":"85"},"type":"corner","text":"Corner,  Sheffield United. Conceded by Ben Nugent.","playerIds":[9348]},{"id":102026,"time":{"secs":4993,"label":"84"},"type":"corner","text":"Corner,  Sheffield United. Conceded by Zoumana Bakayogo.","playerIds":[8969]},{"id":101998,"time":{"secs":4929,"label":"83"},"type":"substitution","text":"Substitution, Sheffield United. Dominic Calvert-Lewin replaces Leon Clarke.","playerIds":[9576,2593]},{"id":102032,"time":{"secs":4847,"label":"81"},"type":"miss","text":"Attempt missed. Oliver Turton (Crewe Alexandra) right footed shot from outside the box is too high.","playerIds":[8484]},{"id":102030,"time":{"secs":4833,"label":"81"},"type":"free kick lost","text":"Foul by Stefan Scougall (Sheffield United).","playerIds":[9572]},{"id":102034,"time":{"secs":4833,"label":"81"},"type":"free kick won","text":"George Cooper (Crewe Alexandra) wins a free kick on the left wing.","playerIds":[10689]},{"id":101967,"time":{"secs":4817,"label":"81"},"type":"corner","text":"Corner,  Crewe Alexandra. Conceded by John Brayford.","playerIds":[4729]},{"id":101953,"time":{"secs":4752,"label":"80"},"type":"attempt blocked","text":"Attempt blocked. Stefan Scougall (Sheffield United) right footed shot from the centre of the box is blocked.","playerIds":[9572]},{"id":101845,"time":{"secs":4540,"label":"76"},"type":"substitution","text":"Substitution, Sheffield United. Stefan Scougall replaces Matt Done.","playerIds":[9572,9489]},{"id":101820,"time":{"secs":4466,"label":"75"},"type":"miss","text":"Attempt missed. Ben Nugent (Crewe Alexandra) header from the centre of the box is close, but misses to the left following a corner.","playerIds":[9348]},{"id":101783,"time":{"secs":4456,"label":"75"},"type":"corner","text":"Corner,  Crewe Alexandra. Conceded by Jack O\u0027Connell.","playerIds":[9491]},{"id":101729,"time":{"secs":4339,"label":"73"},"type":"free kick won","text":"Marc McNulty (Sheffield United) wins a free kick in the defensive half.","playerIds":[10903]},{"id":101730,"time":{"secs":4339,"label":"73"},"type":"free kick lost","text":"Foul by Oliver Turton (Crewe Alexandra).","playerIds":[8484]},{"id":101662,"time":{"secs":4291,"label":"72"},"type":"corner","text":"Corner,  Crewe Alexandra. Conceded by Chris Hussey.","playerIds":[8277]},{"id":101510,"time":{"secs":4156,"label":"70"},"type":"substitution","text":"Substitution, Sheffield United. Marc McNulty replaces Billy Sharp.","playerIds":[10903,4626]},{"id":101250,"time":{"secs":4069,"label":"68"},"type":"substitution","text":"Substitution, Crewe Alexandra. Ryan Lowe replaces Callum Saunders because of an injury.","playerIds":[9905,10694]},{"id":101260,"time":{"secs":4054,"label":"68"},"type":"end delay","text":"Delay over. They are ready to continue."},{"id":101253,"time":{"secs":3955,"label":"66"},"type":"start delay","text":"Delay in match Callum Saunders (Crewe Alexandra) because of an injury."},{"id":101259,"time":{"secs":3886,"label":"65"},"type":"yellow card","text":"Jack O\u0027Connell (Sheffield United) is shown the yellow card for a bad foul.","playerIds":[9491]},{"id":101252,"time":{"secs":3882,"label":"65"},"type":"free kick won","text":"George Cooper (Crewe Alexandra) wins a free kick in the defensive half.","playerIds":[10689]},{"id":101254,"time":{"secs":3882,"label":"65"},"type":"free kick lost","text":"Foul by Jack O\u0027Connell (Sheffield United).","playerIds":[9491]},{"id":101249,"time":{"secs":3820,"label":"64"},"type":"corner","text":"Corner,  Sheffield United. Conceded by George Cooper.","playerIds":[10689]},{"id":101242,"time":{"secs":3749,"label":"63"},"type":"free kick lost","text":"Foul by James Jones (Crewe Alexandra).","playerIds":[10691]},{"id":101255,"time":{"secs":3749,"label":"63"},"type":"free kick won","text":"Mark Duffy (Sheffield United) wins a free kick in the defensive half.","playerIds":[8605]},{"id":101251,"time":{"secs":3647,"label":"61"},"type":"free kick lost","text":"Foul by Billy Sharp (Sheffield United).","playerIds":[4626]},{"id":101256,"time":{"secs":3647,"label":"61"},"type":"free kick won","text":"Ben Nugent (Crewe Alexandra) wins a free kick in the defensive half.","playerIds":[9348]},{"id":101241,"time":{"secs":3490,"label":"59"},"type":"substitution","text":"Substitution, Crewe Alexandra. Alex Kiwomya replaces Charlie Kirk.","playerIds":[10971,13338]},{"id":101258,"time":{"secs":3386,"label":"57"},"type":"miss","text":"Attempt missed. Billy Sharp (Sheffield United) right footed shot from the left side of the box misses to the right.","playerIds":[4626]},{"id":101247,"time":{"secs":3283,"label":"55"},"type":"free kick won","text":"Oliver Turton (Crewe Alexandra) wins a free kick in the defensive half.","playerIds":[8484]},{"id":101248,"time":{"secs":3283,"label":"55"},"type":"free kick lost","text":"Foul by Chris Basham (Sheffield United).","playerIds":[3581]},{"id":101244,"time":{"secs":2943,"label":"50"},"type":"corner","text":"Corner,  Crewe Alexandra. Conceded by Chris Hussey.","playerIds":[8277]},{"id":101245,"time":{"secs":2919,"label":"49"},"type":"free kick won","text":"George Ray (Crewe Alexandra) wins a free kick in the attacking half.","playerIds":[8482]},{"id":101246,"time":{"secs":2919,"label":"49"},"type":"free kick lost","text":"Foul by Billy Sharp (Sheffield United).","playerIds":[4626]},{"id":100551,"time":{"secs":2774,"label":"47"},"type":"free kick won","text":"Jack O\u0027Connell (Sheffield United) wins a free kick in the attacking half.","playerIds":[9491]},{"id":100579,"time":{"secs":2774,"label":"47"},"type":"free kick lost","text":"Foul by Chris Dagnall (Crewe Alexandra).","playerIds":[9000]},{"id":100550,"time":{"secs":2700,"label":"46"},"type":"start","text":"Second Half begins Sheffield United 1, Crewe Alexandra 0."},{"id":100558,"time":{"secs":2700,"label":"46"},"type":"substitution","text":"Substitution, Crewe Alexandra. Perry Ng replaces Billy Bingham.","playerIds":[10687,8507]},{"id":100574,"time":{"secs":2762,"label":"45 +2"},"type":"end 1","text":"First Half ends, Sheffield United 1, Crewe Alexandra 0."},{"id":100572,"time":{"secs":2715,"label":"45 +1"},"type":"free kick won","text":"Oliver Turton (Crewe Alexandra) wins a free kick in the defensive half.","playerIds":[8484]},{"id":100577,"time":{"secs":2715,"label":"45 +1"},"type":"free kick lost","text":"Foul by Chris Hussey (Sheffield United).","playerIds":[8277]},{"id":100560,"time":{"secs":2662,"label":"45"},"type":"miss","text":"Attempt missed. Leon Clarke (Sheffield United) right footed shot from the centre of the box is close, but misses to the right.","playerIds":[2593]},{"id":100565,"time":{"secs":2509,"label":"42"},"type":"corner","text":"Corner,  Sheffield United. Conceded by George Ray.","playerIds":[8482]},{"id":100556,"time":{"secs":2419,"label":"41"},"type":"miss","text":"Attempt missed. George Cooper (Crewe Alexandra) header from the centre of the box is just a bit too high.","playerIds":[10689]},{"id":100555,"time":{"secs":2357,"label":"40"},"type":"free kick lost","text":"Foul by Callum Saunders (Crewe Alexandra).","playerIds":[10694]},{"id":100561,"time":{"secs":2357,"label":"40"},"type":"free kick won","text":"Jack O\u0027Connell (Sheffield United) wins a free kick on the right wing.","playerIds":[9491]},{"id":100557,"time":{"secs":2179,"label":"37"},"type":"free kick won","text":"Oliver Turton (Crewe Alexandra) wins a free kick in the defensive half.","playerIds":[8484]},{"id":100563,"time":{"secs":2179,"label":"37"},"type":"free kick lost","text":"Foul by Billy Sharp (Sheffield United).","playerIds":[4626]},{"id":100567,"time":{"secs":2137,"label":"36"},"type":"corner","text":"Corner,  Crewe Alexandra. Conceded by Jack O\u0027Connell.","playerIds":[9491]},{"id":100578,"time":{"secs":2014,"label":"34"},"type":"miss","text":"Attempt missed. George Cooper (Crewe Alexandra) left footed shot from outside the box is too high.","playerIds":[10689]},{"id":100570,"time":{"secs":1951,"label":"33"},"type":"attempt saved","text":"Attempt saved. Leon Clarke (Sheffield United) left footed shot from the centre of the box is saved in the bottom left corner.","playerIds":[2593]},{"id":100552,"time":{"secs":1860,"label":"32"},"type":"free kick won","text":"George Cooper (Crewe Alexandra) wins a free kick in the defensive half.","playerIds":[10689]},{"id":100553,"time":{"secs":1857,"label":"31"},"type":"free kick lost","text":"Foul by John Fleck (Sheffield United).","playerIds":[8444]},{"id":100568,"time":{"secs":1785,"label":"30"},"type":"attempt blocked","text":"Attempt blocked. John Brayford (Sheffield United) right footed shot from outside the box is blocked.","playerIds":[4729]},{"id":100536,"time":{"secs":1549,"label":"26"},"type":"attempt blocked","text":"Attempt blocked. James Jones (Crewe Alexandra) right footed shot from more than 40 yards on the right wing is blocked.","playerIds":[10691]},{"id":100575,"time":{"secs":1491,"label":"25"},"type":"corner","text":"Corner,  Crewe Alexandra. Conceded by Chris Hussey.","playerIds":[8277]},{"id":100564,"time":{"secs":1412,"label":"24"},"type":"miss","text":"Attempt missed. James Jones (Crewe Alexandra) left footed shot from outside the box is close, but misses to the right.","playerIds":[10691]},{"id":100571,"time":{"secs":1011,"label":"17"},"type":"attempt saved","text":"Attempt saved. John Fleck (Sheffield United) right footed shot from very close range is saved in the centre of the goal.","playerIds":[8444]},{"id":100576,"time":{"secs":915,"label":"16"},"type":"miss","text":"Attempt missed. Leon Clarke (Sheffield United) right footed shot from a difficult angle on the left misses to the right.","playerIds":[2593]},{"id":100562,"time":{"secs":480,"label":"09"},"type":"free kick won","text":"Callum Saunders (Crewe Alexandra) wins a free kick on the right wing.","playerIds":[10694]},{"id":100566,"time":{"secs":477,"label":"08"},"type":"free kick lost","text":"Foul by James Wilson (Sheffield United).","playerIds":[9298]},{"id":100554,"time":{"secs":420,"label":"08"},"type":"free kick won","text":"Jack O\u0027Connell (Sheffield United) wins a free kick in the defensive half.","playerIds":[9491]},{"id":100569,"time":{"secs":417,"label":"07"},"type":"free kick lost","text":"Foul by Chris Dagnall (Crewe Alexandra).","playerIds":[9000]},{"id":100580,"time":{"secs":352,"label":"06"},"type":"goal","text":"Goal!  Sheffield United 1, Crewe Alexandra 0. Leon Clarke (Sheffield United) left footed shot from the centre of the box to the bottom left corner. Assisted by John Fleck.","playerIds":[2593,8444]},{"id":100573,"time":{"secs":315,"label":"06"},"type":"corner","text":"Corner,  Sheffield United. Conceded by Ben Garratt.","playerIds":[8477]},{"id":100559,"time":{"secs":299,"label":"05"},"type":"attempt saved","text":"Attempt saved. Leon Clarke (Sheffield United) right footed shot from the left side of the box is saved in the bottom right corner.","playerIds":[2593]},{"id":98829,"time":{"secs":209,"label":"04"},"type":"attempt saved","text":"Attempt saved. George Cooper (Crewe Alexandra) left footed shot from outside the box is saved in the bottom left corner.","playerIds":[10689]},{"id":101257,"time":{"secs":0,"label":"01"},"type":"start","text":"First Half begins."},{"id":101243,"type":"lineup","text":"Lineups are announced and players are warming up."}]}}