{"fixture":{"gameweek":{"id":2411,"gameweek":39},"kickoff":{"completeness":3,"millis":1337443200000,"label":"Sat 19 May 2012, 17:00 BST","gmtOffset":1.0},"provisionalKickoff":{"completeness":3,"millis":1337443200000,"label":"Sat 19 May 2012, 17:00 BST","gmtOffset":1.0},"teams":[{"team":{"name":"Elche","club":{"name":"Elche","abbr":"ELC","id":628},"teamType":"FIRST","shortName":"Elche","id":770},"score":2},{"team":{"name":"Deportivo Guadalajara","club":{"name":"Deportivo Guadalajara","abbr":"GUA","id":640},"teamType":"FIRST","shortName":"Deportivo Guadalajara","id":782},"score":3}],"replay":false,"ground":{"name":"Martínez Valero","city":"Elche","id":1423},"status":"C","phase":"F","outcome":"A","clock":{"secs":5640,"label":"90 +4\u002700"},"fixtureType":"REGULAR","extraTime":false,"shootout":false,"id":31080},"events":{"pageInfo":{"page":0,"numPages":1,"pageSize":1000,"numEntries":112},"content":[{"id":549344,"time":{"secs":0,"label":"01"},"type":"end 14","text":"Match ends, Elche 2, Deportivo Guadalajara 3."},{"id":549271,"time":{"secs":5606,"label":"90 +4"},"type":"end 2","text":"Second Half ends, Elche 2, Deportivo Guadalajara 3."},{"id":549273,"time":{"secs":5536,"label":"90 +3"},"type":"end delay","text":"Delay over. They are ready to continue."},{"id":549364,"time":{"secs":5500,"label":"90 +2"},"type":"start delay","text":"Delay in match Edu Albácar (Elche) because of an injury."},{"id":549313,"time":{"secs":5473,"label":"90 +2"},"type":"offside","text":"Offside, Deportivo Guadalajara. Ernesto tries a through ball, but Iván Moreno is caught offside.","playerIds":[36799]},{"id":549277,"time":{"secs":5420,"label":"90 +1"},"type":"yellow card","text":"Ernesto (Deportivo Guadalajara) is shown the yellow card for a bad foul.","playerIds":[36799]},{"id":549286,"time":{"secs":5419,"label":"90 +1"},"type":"free kick won","text":"Jordi Xumetra (Elche) wins a free kick in the defensive half.","playerIds":[36308]},{"id":549365,"time":{"secs":5419,"label":"90 +1"},"type":"free kick lost","text":"Foul by Ernesto (Deportivo Guadalajara).","playerIds":[36799]},{"id":549279,"time":{"secs":5383,"label":"90"},"type":"free kick won","text":"Rodri (Deportivo Guadalajara) wins a free kick in the defensive half.","playerIds":[36249]},{"id":549322,"time":{"secs":5383,"label":"90"},"type":"free kick lost","text":"Foul by Rúper (Elche).","playerIds":[35992]},{"id":549363,"time":{"secs":5309,"label":"89"},"type":"offside","text":"Offside, Elche. Jordi Xumetra tries a through ball, but Ángel Rodríguez is caught offside.","playerIds":[36308]},{"id":549283,"time":{"secs":5182,"label":"87"},"type":"yellow card","text":"Javi Barral (Deportivo Guadalajara) is shown the yellow card for a bad foul.","playerIds":[36793]},{"id":549323,"time":{"secs":5177,"label":"87"},"type":"free kick won","text":"Jordi Xumetra (Elche) wins a free kick in the defensive half.","playerIds":[36308]},{"id":549336,"time":{"secs":5177,"label":"87"},"type":"free kick lost","text":"Foul by Javi Barral (Deportivo Guadalajara).","playerIds":[36793]},{"id":549310,"time":{"secs":5011,"label":"84"},"type":"attempt saved","text":"Attempt saved. David Generelo (Elche) right footed shot from outside the box is saved in the centre of the goal. Assisted by Jordi Xumetra.","playerIds":[36309,36308]},{"id":549346,"time":{"secs":4887,"label":"82"},"type":"miss","text":"Attempt missed. Ernesto (Deportivo Guadalajara) left footed shot from outside the box is close, but misses the top right corner from a direct free kick.","playerIds":[36799]},{"id":549338,"time":{"secs":4851,"label":"81"},"type":"free kick lost","text":"Foul by Rúper (Elche).","playerIds":[35992]},{"id":549345,"time":{"secs":4851,"label":"81"},"type":"free kick won","text":"Rodri (Deportivo Guadalajara) wins a free kick in the attacking half.","playerIds":[36249]},{"id":549297,"time":{"secs":4769,"label":"80"},"type":"miss","text":"Attempt missed. David Generelo (Elche) right footed shot from outside the box misses to the left. Assisted by Edu Albácar following a set piece situation.","playerIds":[36309,36300]},{"id":549280,"time":{"secs":4743,"label":"80"},"type":"yellow card","text":"Ander Gago (Deportivo Guadalajara) is shown the yellow card for a bad foul.","playerIds":[36797]},{"id":549312,"time":{"secs":4740,"label":"80"},"type":"free kick won","text":"Miguel Palanca (Elche) wins a free kick on the left wing.","playerIds":[36305]},{"id":549324,"time":{"secs":4740,"label":"80"},"type":"free kick lost","text":"Foul by Ander Gago (Deportivo Guadalajara).","playerIds":[36797]},{"id":549337,"time":{"secs":4723,"label":"79"},"type":"free kick won","text":"Héctor Rodas (Elche) wins a free kick in the defensive half.","playerIds":[35918]},{"id":549366,"time":{"secs":4723,"label":"79"},"type":"free kick lost","text":"Foul by Aníbal (Deportivo Guadalajara).","playerIds":[36805]},{"id":549370,"time":{"secs":4626,"label":"78"},"type":"miss","text":"Attempt missed. Javi Soria (Deportivo Guadalajara) header from the centre of the box is high and wide to the right. Assisted by Ernesto with a cross following a set piece situation.","playerIds":[36796,36799]},{"id":549301,"time":{"secs":4578,"label":"77"},"type":"yellow card","text":"Edu Albácar (Elche) is shown the yellow card for a bad foul.","playerIds":[36300]},{"id":549294,"time":{"secs":4572,"label":"77"},"type":"free kick won","text":"Iván Moreno (Deportivo Guadalajara) wins a free kick on the right wing.","playerIds":[36801]},{"id":549358,"time":{"secs":4572,"label":"77"},"type":"free kick lost","text":"Foul by Edu Albácar (Elche).","playerIds":[36300]},{"id":549330,"time":{"secs":4377,"label":"73"},"type":"goal","text":"Goal!  Elche 2, Deportivo Guadalajara 3. Ángel Rodríguez (Elche) header from very close range to the top right corner. Assisted by Nicki Bille Nielsen with a cross following a fast break.","playerIds":[25963,15880]},{"id":549282,"time":{"secs":4307,"label":"72"},"type":"free kick lost","text":"Foul by Miguel Palanca (Elche).","playerIds":[36305]},{"id":549308,"time":{"secs":4307,"label":"72"},"type":"free kick won","text":"Jonan García (Deportivo Guadalajara) wins a free kick on the right wing.","playerIds":[36802]},{"id":549289,"time":{"secs":4216,"label":"71"},"type":"substitution","text":"Substitution, Deportivo Guadalajara. Ernesto replaces Víctor Fernández.","playerIds":[36799,35342]},{"id":549307,"time":{"secs":4152,"label":"70"},"type":"attempt saved","text":"Attempt saved. Jordi Xumetra (Elche) right footed shot from the right side of the box is saved in the centre of the goal. Assisted by David Generelo with a cross.","playerIds":[36308,36309]},{"id":549321,"time":{"secs":4137,"label":"69"},"type":"free kick won","text":"Nicki Bille Nielsen (Elche) wins a free kick on the left wing.","playerIds":[15880]},{"id":549371,"time":{"secs":4137,"label":"69"},"type":"free kick lost","text":"Foul by Mikael Gaffoor (Deportivo Guadalajara).","playerIds":[36795]},{"id":549377,"time":{"secs":4118,"label":"69"},"type":"end delay","text":"Delay over. They are ready to continue."},{"id":549362,"time":{"secs":4085,"label":"69"},"type":"start delay","text":"Delay in match Víctor Fernández (Deportivo Guadalajara) because of an injury."},{"id":549342,"time":{"secs":3922,"label":"66"},"type":"end delay","text":"Delay over. They are ready to continue."},{"id":549356,"time":{"secs":3870,"label":"65"},"type":"start delay","text":"Delay in match Héctor Rodas (Elche) because of an injury."},{"id":549291,"time":{"secs":3791,"label":"64"},"type":"miss","text":"Attempt missed. Rodri (Deportivo Guadalajara) right footed shot from a difficult angle on the right is close, but misses to the right. Assisted by Iván Moreno.","playerIds":[36249,36801]},{"id":549303,"time":{"secs":3567,"label":"60"},"type":"miss","text":"Attempt missed. Nicki Bille Nielsen (Elche) left footed shot from a difficult angle on the left is close, but misses to the left following a fast break.","playerIds":[15880]},{"id":549309,"time":{"secs":3492,"label":"59"},"type":"offside","text":"Offside, Deportivo Guadalajara. Jonan García tries a through ball, but Aníbal is caught offside.","playerIds":[36802]},{"id":549287,"time":{"secs":3305,"label":"56"},"type":"substitution","text":"Substitution, Deportivo Guadalajara. Ander Gago replaces Antonio Moreno.","playerIds":[36797,36792]},{"id":549300,"time":{"secs":3278,"label":"55"},"type":"offside","text":"Offside, Deportivo Guadalajara. Jonan García tries a through ball, but Aníbal is caught offside.","playerIds":[36802]},{"id":549326,"time":{"secs":3139,"label":"53"},"type":"offside","text":"Offside, Deportivo Guadalajara. Javi Barral tries a through ball, but Rodri is caught offside.","playerIds":[36793]},{"id":549354,"time":{"secs":3097,"label":"52"},"type":"corner","text":"Corner,  Deportivo Guadalajara. Conceded by Xabier Etxeita.","playerIds":[11047]},{"id":549332,"time":{"secs":3033,"label":"51"},"type":"corner","text":"Corner,  Elche. Conceded by Mikael Gaffoor.","playerIds":[36795]},{"id":549276,"time":{"secs":3009,"label":"51"},"type":"substitution","text":"Substitution, Deportivo Guadalajara. Iván Moreno replaces Cristian Fernández.","playerIds":[36801,36197]},{"id":549328,"time":{"secs":2974,"label":"50"},"type":"miss","text":"Attempt missed. Edu Albácar (Elche) left footed shot from outside the box is just a bit too high from a direct free kick.","playerIds":[36300]},{"id":549304,"time":{"secs":2920,"label":"49"},"type":"yellow card","text":"Antonio Moreno (Deportivo Guadalajara) is shown the yellow card for a bad foul.","playerIds":[36792]},{"id":549295,"time":{"secs":2907,"label":"49"},"type":"free kick won","text":"Ángel Rodríguez (Elche) wins a free kick in the attacking half.","playerIds":[25963]},{"id":549311,"time":{"secs":2907,"label":"49"},"type":"free kick lost","text":"Foul by Antonio Moreno (Deportivo Guadalajara).","playerIds":[36792]},{"id":549327,"time":{"secs":2870,"label":"48"},"type":"free kick lost","text":"Foul by Rodri (Deportivo Guadalajara).","playerIds":[36249]},{"id":549343,"time":{"secs":2870,"label":"48"},"type":"free kick won","text":"Ángel Rodríguez (Elche) wins a free kick in the defensive half.","playerIds":[25963]},{"id":549281,"time":{"secs":2840,"label":"48"},"type":"free kick lost","text":"Foul by Jony (Deportivo Guadalajara).","playerIds":[12715]},{"id":549305,"time":{"secs":2840,"label":"48"},"type":"free kick won","text":"David Generelo (Elche) wins a free kick in the defensive half.","playerIds":[36309]},{"id":549376,"time":{"secs":2817,"label":"47"},"type":"free kick won","text":"Edu Albácar (Elche) wins a free kick on the left wing.","playerIds":[36300]},{"id":549357,"time":{"secs":2817,"label":"47"},"type":"free kick lost","text":"Foul by Cristian Fernández (Deportivo Guadalajara).","playerIds":[36197]},{"id":549292,"time":{"secs":2716,"label":"46"},"type":"attempt saved","text":"Attempt saved. Víctor Fernández (Deportivo Guadalajara) left footed shot from outside the box is saved in the centre of the goal. Assisted by Jonan García.","playerIds":[35342,36802]},{"id":549293,"time":{"secs":2700,"label":"46"},"type":"substitution","text":"Substitution, Elche. Rúper replaces Grégory Béranger.","playerIds":[35992,36616]},{"id":549302,"time":{"secs":2700,"label":"46"},"type":"start","text":"Second Half begins Elche 1, Deportivo Guadalajara 3."},{"id":549375,"time":{"secs":2700,"label":"46"},"type":"substitution","text":"Substitution, Elche. Miguel Palanca replaces Yeray Patino.","playerIds":[36305,36813]},{"id":549299,"time":{"secs":2764,"label":"45 +2"},"type":"end 1","text":"First Half ends, Elche 1, Deportivo Guadalajara 3."},{"id":549360,"time":{"secs":2544,"label":"43"},"type":"corner","text":"Corner,  Deportivo Guadalajara. Conceded by Xabier Etxeita.","playerIds":[11047]},{"id":549335,"time":{"secs":2234,"label":"38"},"type":"yellow card","text":"Cristian Fernández (Deportivo Guadalajara) is shown the yellow card for a bad foul.","playerIds":[36197]},{"id":549359,"time":{"secs":2231,"label":"38"},"type":"free kick won","text":"Edu Albácar (Elche) wins a free kick in the defensive half.","playerIds":[36300]},{"id":549369,"time":{"secs":2231,"label":"38"},"type":"free kick lost","text":"Foul by Cristian Fernández (Deportivo Guadalajara).","playerIds":[36197]},{"id":549298,"time":{"secs":2197,"label":"37"},"type":"free kick lost","text":"Foul by Aníbal (Deportivo Guadalajara).","playerIds":[36805]},{"id":549367,"time":{"secs":2197,"label":"37"},"type":"free kick won","text":"Jordi Xumetra (Elche) wins a free kick in the attacking half.","playerIds":[36308]},{"id":549380,"time":{"secs":2070,"label":"35"},"type":"miss","text":"Attempt missed. Rodri (Deportivo Guadalajara) right footed shot from the centre of the box is just a bit too high. Assisted by Jonan García.","playerIds":[36249,36802]},{"id":549288,"time":{"secs":1964,"label":"33"},"type":"free kick won","text":"Grégory Béranger (Elche) wins a free kick in the defensive half.","playerIds":[36616]},{"id":549331,"time":{"secs":1964,"label":"33"},"type":"free kick lost","text":"Foul by Rodri (Deportivo Guadalajara).","playerIds":[36249]},{"id":549378,"time":{"secs":1859,"label":"31"},"type":"corner","text":"Corner,  Deportivo Guadalajara. Conceded by Sergio Mantecón.","playerIds":[36303]},{"id":549329,"time":{"secs":1749,"label":"30"},"type":"miss","text":"Attempt missed. David Generelo (Elche) right footed shot from outside the box is too high. Assisted by Sergio Mantecón.","playerIds":[36309,36303]},{"id":549351,"time":{"secs":1639,"label":"28"},"type":"own goal","text":"Own Goal by Héctor Rodas, Elche.  Elche 1, Deportivo Guadalajara 3.","playerIds":[35918]},{"id":549333,"time":{"secs":1638,"label":"28"},"type":"post","text":"Javi Barral (Deportivo Guadalajara) hits the bar with a header from very close range following a set piece situation.","playerIds":[36793]},{"id":549361,"time":{"secs":1636,"label":"28"},"type":"attempt saved","text":"Attempt saved. Víctor Fernández (Deportivo Guadalajara) left footed shot from a difficult angle and long range on the right is saved in the bottom right corner.","playerIds":[35342]},{"id":549272,"time":{"secs":1587,"label":"27"},"type":"free kick won","text":"Rodri (Deportivo Guadalajara) wins a free kick on the right wing.","playerIds":[36249]},{"id":549318,"time":{"secs":1587,"label":"27"},"type":"free kick lost","text":"Foul by David Generelo (Elche).","playerIds":[36309]},{"id":549381,"time":{"secs":1520,"label":"26"},"type":"free kick won","text":"Jony (Deportivo Guadalajara) wins a free kick in the defensive half.","playerIds":[12715]},{"id":549306,"time":{"secs":1520,"label":"26"},"type":"free kick lost","text":"Foul by Nicki Bille Nielsen (Elche).","playerIds":[15880]},{"id":549319,"time":{"secs":1350,"label":"23"},"type":"miss","text":"Attempt missed. Jordi Xumetra (Elche) left footed shot from the centre of the box is close, but misses to the right following a fast break.","playerIds":[36308]},{"id":549290,"time":{"secs":1303,"label":"22"},"type":"free kick lost","text":"Foul by Edu Albácar (Elche).","playerIds":[36300]},{"id":549348,"time":{"secs":1303,"label":"22"},"type":"free kick won","text":"Antonio Moreno (Deportivo Guadalajara) wins a free kick in the defensive half.","playerIds":[36792]},{"id":549347,"time":{"secs":1281,"label":"22"},"type":"free kick won","text":"Nicki Bille Nielsen (Elche) wins a free kick on the right wing.","playerIds":[15880]},{"id":549372,"time":{"secs":1281,"label":"22"},"type":"free kick lost","text":"Foul by Jony (Deportivo Guadalajara).","playerIds":[12715]},{"id":549339,"time":{"secs":1239,"label":"21"},"type":"free kick won","text":"Edu Albácar (Elche) wins a free kick in the defensive half.","playerIds":[36300]},{"id":549349,"time":{"secs":1239,"label":"21"},"type":"free kick lost","text":"Foul by Rodri (Deportivo Guadalajara).","playerIds":[36249]},{"id":549274,"time":{"secs":1078,"label":"18"},"type":"goal","text":"Goal!  Elche 1, Deportivo Guadalajara 2. Javi Soria (Deportivo Guadalajara) header from the centre of the box to the top right corner. Assisted by Víctor Fernández with a cross following a corner.","playerIds":[36796,35342]},{"id":549373,"time":{"secs":1049,"label":"18"},"type":"corner","text":"Corner,  Deportivo Guadalajara. Conceded by Sergio Mantecón.","playerIds":[36303]},{"id":549284,"time":{"secs":1016,"label":"17"},"type":"free kick won","text":"Mikael Gaffoor (Deportivo Guadalajara) wins a free kick in the defensive half.","playerIds":[36795]},{"id":549352,"time":{"secs":1016,"label":"17"},"type":"free kick lost","text":"Foul by Ángel Rodríguez (Elche).","playerIds":[25963]},{"id":549317,"time":{"secs":946,"label":"16"},"type":"attempt saved","text":"Attempt saved. Javi Soria (Deportivo Guadalajara) right footed shot from outside the box is saved in the centre of the goal.","playerIds":[36796]},{"id":549278,"time":{"secs":889,"label":"15"},"type":"free kick lost","text":"Foul by Héctor Rodas (Elche).","playerIds":[35918]},{"id":549314,"time":{"secs":889,"label":"15"},"type":"free kick won","text":"Rodri (Deportivo Guadalajara) wins a free kick in the attacking half.","playerIds":[36249]},{"id":549353,"time":{"secs":826,"label":"14"},"type":"goal","text":"Goal!  Elche 1, Deportivo Guadalajara 1. Rodri (Deportivo Guadalajara) converts the penalty with a right footed shot to the bottom right corner.","playerIds":[36249]},{"id":549368,"time":{"secs":778,"label":"13"},"type":"yellow card","text":"Sergio Mantecón (Elche) is shown the yellow card for a bad foul.","playerIds":[36303]},{"id":549275,"time":{"secs":764,"label":"13"},"type":"penalty lost","text":"Penalty conceded by Sergio Mantecón (Elche) after a foul in the penalty area.","playerIds":[36303]},{"id":549340,"time":{"secs":764,"label":"13"},"type":"penalty won","text":"Penalty Deportivo Guadalajara. Jonan García draws a foul in the penalty area.","playerIds":[36802]},{"id":549316,"time":{"secs":712,"label":"12"},"type":"free kick lost","text":"Foul by Edu Albácar (Elche).","playerIds":[36300]},{"id":549350,"time":{"secs":712,"label":"12"},"type":"free kick won","text":"Rodri (Deportivo Guadalajara) wins a free kick in the attacking half.","playerIds":[36249]},{"id":549296,"time":{"secs":690,"label":"12"},"type":"attempt saved","text":"Attempt saved. Rodri (Deportivo Guadalajara) right footed shot from outside the box is saved in the bottom right corner. Assisted by Jony.","playerIds":[36249,12715]},{"id":549341,"time":{"secs":436,"label":"08"},"type":"corner","text":"Corner,  Deportivo Guadalajara. Conceded by David Generelo.","playerIds":[36309]},{"id":549320,"time":{"secs":402,"label":"07"},"type":"corner","text":"Corner,  Deportivo Guadalajara. Conceded by Sergio Mantecón.","playerIds":[36303]},{"id":549315,"time":{"secs":274,"label":"05"},"type":"offside","text":"Offside, Elche. Jordi Xumetra tries a through ball, but Nicki Bille Nielsen is caught offside.","playerIds":[36308]},{"id":549325,"time":{"secs":253,"label":"05"},"type":"free kick won","text":"Mikael Gaffoor (Deportivo Guadalajara) wins a free kick in the defensive half.","playerIds":[36795]},{"id":549334,"time":{"secs":253,"label":"05"},"type":"free kick lost","text":"Foul by Jordi Xumetra (Elche).","playerIds":[36308]},{"id":549285,"time":{"secs":136,"label":"03"},"type":"free kick won","text":"Nicki Bille Nielsen (Elche) wins a free kick on the right wing.","playerIds":[15880]},{"id":549355,"time":{"secs":136,"label":"03"},"type":"free kick lost","text":"Foul by Javi Soria (Deportivo Guadalajara).","playerIds":[36796]},{"id":549270,"time":{"secs":65,"label":"02"},"type":"goal","text":"Goal!  Elche 1, Deportivo Guadalajara 0. Ángel Rodríguez (Elche) left footed shot from the left side of the box to the bottom right corner. Assisted by Nicki Bille Nielsen with a through ball following a fast break.","playerIds":[25963,15880]},{"id":549374,"time":{"secs":0,"label":"01"},"type":"start","text":"First Half begins."},{"id":549379,"type":"lineup","text":"Lineups are announced and players are warming up."}]}}