{"fixture":{"gameweek":{"id":2494,"gameweek":30},"kickoff":{"completeness":3,"millis":1394902800000,"label":"Sat 15 Mar 2014, 17:00 GMT"},"provisionalKickoff":{"completeness":3,"millis":1394902800000,"label":"Sat 15 Mar 2014, 17:00 GMT"},"teams":[{"team":{"name":"Real Jaén","club":{"name":"Real Jaén","abbr":"JAE","id":648},"teamType":"FIRST","shortName":"Jaén","id":790},"score":3},{"team":{"name":"Sporting de Gijón","club":{"name":"Sporting de Gijón","abbr":"SPG","id":621},"teamType":"FIRST","shortName":"Sporting de Gijón","id":762},"score":2}],"replay":false,"ground":{"name":"Nuevo Estadio de La Victoria","city":"Jaén","id":1431},"status":"C","phase":"F","outcome":"H","attendance":8500,"clock":{"secs":5580,"label":"90 +3\u002700"},"fixtureType":"REGULAR","extraTime":false,"shootout":false,"id":31918},"events":{"pageInfo":{"page":0,"numPages":1,"pageSize":1000,"numEntries":122},"content":[{"id":648950,"time":{"secs":0,"label":"01"},"type":"end 14","text":"Match ends, Real Jaén 3, Sporting de Gijón 2."},{"id":648919,"time":{"secs":5570,"label":"90 +3"},"type":"end 2","text":"Second Half ends, Real Jaén 3, Sporting de Gijón 2."},{"id":648942,"time":{"secs":5543,"label":"90 +3"},"type":"offside","text":"Offside, Real Jaén. Fran Machado tries a through ball, but Víctor Curto is caught offside.","playerIds":[37251]},{"id":649011,"time":{"secs":5428,"label":"90 +1"},"type":"free kick lost","text":"Dangerous play by Óscar Rico (Real Jaén).","playerIds":[37252]},{"id":649023,"time":{"secs":5428,"label":"90 +1"},"type":"free kick won","text":"Cristian Bustos (Sporting de Gijón) wins a free kick in the defensive half.","playerIds":[36268]},{"id":648970,"time":{"secs":5327,"label":"89"},"type":"miss","text":"Attempt missed. Formose Mendy (Sporting de Gijón) right footed shot from the right side of the box is high and wide to the right following a set piece situation.","playerIds":[10581]},{"id":649001,"time":{"secs":5292,"label":"89"},"type":"free kick lost","text":"Foul by Ritchie Kitoko (Real Jaén).","playerIds":[12038]},{"id":648936,"time":{"secs":5292,"label":"89"},"type":"free kick won","text":"Dejan Lekic (Sporting de Gijón) wins a free kick on the left wing.","playerIds":[36000]},{"id":649027,"time":{"secs":5269,"label":"88"},"type":"miss","text":"Attempt missed. Óscar Rico (Real Jaén) left footed shot from the left side of the box misses to the right.","playerIds":[37252]},{"id":649028,"time":{"secs":5265,"label":"88"},"type":"attempt saved","text":"Attempt saved. Fran Machado (Real Jaén) right footed shot from the left side of the six yard box is saved in the centre of the goal.","playerIds":[37251]},{"id":648962,"time":{"secs":5225,"label":"88"},"type":"corner","text":"Corner,  Real Jaén. Conceded by Iván Cuéllar.","playerIds":[26071]},{"id":649004,"time":{"secs":5223,"label":"88"},"type":"attempt saved","text":"Attempt saved. Víctor Curto (Real Jaén) left footed shot from the left side of the box is saved in the bottom left corner. Assisted by Óscar Rico.","playerIds":[36366,37252]},{"id":649009,"time":{"secs":5175,"label":"87"},"type":"free kick lost","text":"Foul by Mandi (Sporting de Gijón).","playerIds":[36028]},{"id":649019,"time":{"secs":5175,"label":"87"},"type":"free kick won","text":"Víctor Curto (Real Jaén) wins a free kick on the right wing.","playerIds":[36366]},{"id":649035,"time":{"secs":5105,"label":"86"},"type":"miss","text":"Attempt missed. Nacho Cases (Sporting de Gijón) left footed shot from outside the box is just a bit too high. Assisted by Alberto Lora.","playerIds":[36090,36079]},{"id":648963,"time":{"secs":5096,"label":"85"},"type":"substitution","text":"Substitution, Real Jaén. Raúl Gaitán replaces Jona because of an injury.","playerIds":[37242,37256]},{"id":648998,"time":{"secs":4936,"label":"83"},"type":"goal","text":"Goal!  Real Jaén 3, Sporting de Gijón 2. Jona (Real Jaén) header from the centre of the box to the high centre of the goal. Assisted by Víctor Curto with a cross.","playerIds":[37256,36366]},{"id":648971,"time":{"secs":4931,"label":"83"},"type":"attempt blocked","text":"Attempt blocked. Jozabed Sánchez (Real Jaén) right footed shot from the centre of the box is blocked. Assisted by Fran Machado.","playerIds":[19861,37251]},{"id":648989,"time":{"secs":4821,"label":"81"},"type":"free kick lost","text":"Foul by Juanma (Real Jaén).","playerIds":[37250]},{"id":648958,"time":{"secs":4821,"label":"81"},"type":"free kick won","text":"Nacho Cases (Sporting de Gijón) wins a free kick in the defensive half.","playerIds":[36090]},{"id":648983,"time":{"secs":4767,"label":"80"},"type":"free kick won","text":"Stefan Scepovic (Sporting de Gijón) wins a free kick in the defensive half.","playerIds":[12190]},{"id":648990,"time":{"secs":4767,"label":"80"},"type":"free kick lost","text":"Foul by Ritchie Kitoko (Real Jaén).","playerIds":[12038]},{"id":648927,"time":{"secs":4726,"label":"79"},"type":"yellow card","text":"Sergio Álvarez (Sporting de Gijón) is shown the yellow card for a bad foul.","playerIds":[36088]},{"id":648997,"time":{"secs":4715,"label":"79"},"type":"free kick lost","text":"Foul by Sergio Álvarez (Sporting de Gijón).","playerIds":[36088]},{"id":648918,"time":{"secs":4715,"label":"79"},"type":"free kick won","text":"Víctor Curto (Real Jaén) wins a free kick in the defensive half.","playerIds":[36366]},{"id":649036,"time":{"secs":4668,"label":"78"},"type":"substitution","text":"Substitution, Real Jaén. Víctor Curto replaces Israel Jerez.","playerIds":[36366,39095]},{"id":648951,"time":{"secs":4578,"label":"77"},"type":"miss","text":"Attempt missed. Dejan Lekic (Sporting de Gijón) right footed shot from outside the box is high and wide to the right. Assisted by Nacho Cases.","playerIds":[36000,36090]},{"id":649025,"time":{"secs":4463,"label":"75"},"type":"miss","text":"Attempt missed. Sergio Álvarez (Sporting de Gijón) right footed shot from the right side of the box is high and wide to the right. Assisted by Nacho Cases with a headed pass.","playerIds":[36088,36090]},{"id":648986,"time":{"secs":4416,"label":"74"},"type":"miss","text":"Attempt missed. Israel Jerez (Real Jaén) left footed shot from the centre of the box is high and wide to the left. Assisted by Juanma.","playerIds":[39095,37250]},{"id":649002,"time":{"secs":4297,"label":"72"},"type":"corner","text":"Corner,  Real Jaén. Conceded by Formose Mendy.","playerIds":[10581]},{"id":648980,"time":{"secs":4192,"label":"70"},"type":"goal","text":"Goal!  Real Jaén 2, Sporting de Gijón 2. Stefan Scepovic (Sporting de Gijón) right footed shot from the centre of the box to the centre of the goal. Assisted by Nacho Cases.","playerIds":[12190,36090]},{"id":648933,"time":{"secs":4110,"label":"69"},"type":"substitution","text":"Substitution, Sporting de Gijón. Cristian Bustos replaces Carlos Carmona.","playerIds":[36268,36226]},{"id":648999,"time":{"secs":4094,"label":"69"},"type":"yellow card","text":"Mandi (Sporting de Gijón) is shown the yellow card.","playerIds":[36028]},{"id":648929,"time":{"secs":4037,"label":"68"},"type":"goal","text":"Goal!  Real Jaén 2, Sporting de Gijón 1. Óscar Rico (Real Jaén) left footed shot from the centre of the box to the high centre of the goal. Assisted by Jozabed Sánchez.","playerIds":[37252,19861]},{"id":648966,"time":{"secs":3889,"label":"65"},"type":"offside","text":"Offside, Real Jaén. José Cruz tries a through ball, but Fran Machado is caught offside.","playerIds":[37243]},{"id":648930,"time":{"secs":3870,"label":"65"},"type":"corner","text":"Corner,  Real Jaén. Conceded by Bernardo Espinosa.","playerIds":[19601]},{"id":648952,"time":{"secs":3760,"label":"63"},"type":"free kick won","text":"Jona (Real Jaén) wins a free kick in the attacking half.","playerIds":[37256]},{"id":648957,"time":{"secs":3760,"label":"63"},"type":"free kick lost","text":"Foul by Bernardo Espinosa (Sporting de Gijón).","playerIds":[19601]},{"id":648975,"time":{"secs":3713,"label":"62"},"type":"miss","text":"Attempt missed. Mandi (Sporting de Gijón) right footed shot from more than 35 yards is high and wide to the right. Assisted by Carlos Carmona.","playerIds":[36028,36226]},{"id":649013,"time":{"secs":3676,"label":"62"},"type":"free kick won","text":"Stefan Scepovic (Sporting de Gijón) wins a free kick on the left wing.","playerIds":[12190]},{"id":648920,"time":{"secs":3676,"label":"62"},"type":"free kick lost","text":"Foul by Óscar Quesada (Real Jaén).","playerIds":[37253]},{"id":648949,"time":{"secs":3560,"label":"60"},"type":"corner","text":"Corner,  Real Jaén. Conceded by Roberto Canella.","playerIds":[36081]},{"id":648982,"time":{"secs":3478,"label":"58"},"type":"free kick won","text":"Ritchie Kitoko (Real Jaén) wins a free kick on the right wing.","playerIds":[12038]},{"id":648938,"time":{"secs":3478,"label":"58"},"type":"free kick lost","text":"Foul by Formose Mendy (Sporting de Gijón).","playerIds":[10581]},{"id":648937,"time":{"secs":3466,"label":"58"},"type":"attempt blocked","text":"Attempt blocked. Israel Jerez (Real Jaén) left footed shot from outside the box is blocked. Assisted by Juanma.","playerIds":[39095,37250]},{"id":648916,"time":{"secs":3434,"label":"58"},"type":"free kick won","text":"Sergio Álvarez (Sporting de Gijón) wins a free kick in the defensive half.","playerIds":[36088]},{"id":648954,"time":{"secs":3434,"label":"58"},"type":"free kick lost","text":"Foul by Juanma (Real Jaén).","playerIds":[37250]},{"id":649021,"time":{"secs":3376,"label":"57"},"type":"miss","text":"Attempt missed. Óscar Rico (Real Jaén) left footed shot from the left side of the box is close, but misses to the left. Assisted by Fran Machado with a headed pass.","playerIds":[37252,37251]},{"id":648959,"time":{"secs":3334,"label":"56"},"type":"miss","text":"Attempt missed. Formose Mendy (Sporting de Gijón) right footed shot from outside the box is high and wide to the right following a corner.","playerIds":[10581]},{"id":648964,"time":{"secs":3300,"label":"56"},"type":"corner","text":"Corner,  Sporting de Gijón. Conceded by Nando.","playerIds":[37248]},{"id":648947,"time":{"secs":3267,"label":"55"},"type":"free kick won","text":"Juanma (Real Jaén) wins a free kick in the defensive half.","playerIds":[37250]},{"id":648956,"time":{"secs":3267,"label":"55"},"type":"free kick lost","text":"Foul by Sergio Álvarez (Sporting de Gijón).","playerIds":[36088]},{"id":648991,"time":{"secs":3180,"label":"54"},"type":"offside","text":"Offside, Sporting de Gijón. Carlos Carmona tries a through ball, but Dejan Lekic is caught offside.","playerIds":[36226]},{"id":648978,"time":{"secs":3139,"label":"53"},"type":"free kick won","text":"René (Real Jaén) wins a free kick in the defensive half.","playerIds":[26437]},{"id":648931,"time":{"secs":3139,"label":"53"},"type":"free kick lost","text":"Foul by Mandi (Sporting de Gijón).","playerIds":[36028]},{"id":649037,"time":{"secs":3107,"label":"52"},"type":"corner","text":"Corner,  Sporting de Gijón. Conceded by René.","playerIds":[26437]},{"id":648972,"time":{"secs":3059,"label":"51"},"type":"free kick lost","text":"Foul by Carlos Carmona (Sporting de Gijón).","playerIds":[36226]},{"id":648939,"time":{"secs":3059,"label":"51"},"type":"free kick won","text":"Israel Jerez (Real Jaén) wins a free kick in the defensive half.","playerIds":[39095]},{"id":648948,"time":{"secs":3006,"label":"51"},"type":"miss","text":"Attempt missed. Jozabed Sánchez (Real Jaén) right footed shot from outside the box is close, but misses to the right. Assisted by Juanma.","playerIds":[19861,37250]},{"id":648976,"time":{"secs":2939,"label":"49"},"type":"yellow card","text":"Alberto Lora (Sporting de Gijón) is shown the yellow card for a bad foul.","playerIds":[36079]},{"id":648988,"time":{"secs":2919,"label":"49"},"type":"free kick lost","text":"Foul by Alberto Lora (Sporting de Gijón).","playerIds":[36079]},{"id":649010,"time":{"secs":2919,"label":"49"},"type":"free kick won","text":"Óscar Rico (Real Jaén) wins a free kick in the attacking half.","playerIds":[37252]},{"id":648981,"time":{"secs":2848,"label":"48"},"type":"corner","text":"Corner,  Real Jaén. Conceded by Iván Cuéllar.","playerIds":[26071]},{"id":649020,"time":{"secs":2847,"label":"48"},"type":"attempt saved","text":"Attempt saved. Fran Machado (Real Jaén) left footed shot from the centre of the box is saved in the bottom left corner.","playerIds":[37251]},{"id":648965,"time":{"secs":2845,"label":"48"},"type":"attempt saved","text":"Attempt saved. Jona (Real Jaén) right footed shot from the centre of the box is saved in the centre of the goal. Assisted by Fran Machado.","playerIds":[37256,37251]},{"id":649006,"time":{"secs":2700,"label":"46"},"type":"substitution","text":"Substitution, Sporting de Gijón. Dejan Lekic replaces Luis Hernández.","playerIds":[36000,19599]},{"id":648921,"time":{"secs":2700,"label":"46"},"type":"start","text":"Second Half begins Real Jaén 1, Sporting de Gijón 1."},{"id":649026,"time":{"secs":2820,"label":"45 +3"},"type":"end 1","text":"First Half ends, Real Jaén 1, Sporting de Gijón 1."},{"id":648973,"time":{"secs":2771,"label":"45 +2"},"type":"free kick won","text":"Carlos Carmona (Sporting de Gijón) wins a free kick in the defensive half.","playerIds":[36226]},{"id":648987,"time":{"secs":2771,"label":"45 +2"},"type":"free kick lost","text":"Foul by Ritchie Kitoko (Real Jaén).","playerIds":[12038]},{"id":648967,"time":{"secs":2702,"label":"45 +1"},"type":"free kick won","text":"Fran Machado (Real Jaén) wins a free kick on the right wing.","playerIds":[37251]},{"id":648979,"time":{"secs":2702,"label":"45 +1"},"type":"free kick lost","text":"Foul by Mandi (Sporting de Gijón).","playerIds":[36028]},{"id":649008,"time":{"secs":2652,"label":"45"},"type":"miss","text":"Attempt missed. Formose Mendy (Sporting de Gijón) right footed shot from the left side of the box is high and wide to the right. Assisted by Roberto Canella.","playerIds":[10581,36081]},{"id":648968,"time":{"secs":2585,"label":"44"},"type":"corner","text":"Corner,  Sporting de Gijón. Conceded by Óscar Quesada.","playerIds":[37253]},{"id":648995,"time":{"secs":2544,"label":"43"},"type":"corner","text":"Corner,  Sporting de Gijón. Conceded by Ritchie Kitoko.","playerIds":[12038]},{"id":649029,"time":{"secs":2416,"label":"41"},"type":"corner","text":"Corner,  Sporting de Gijón. Conceded by Nando.","playerIds":[37248]},{"id":648969,"time":{"secs":2413,"label":"41"},"type":"attempt saved","text":"Attempt saved. Formose Mendy (Sporting de Gijón) right footed shot from the left side of the box is saved in the bottom right corner. Assisted by Stefan Scepovic.","playerIds":[10581,12190]},{"id":648940,"time":{"secs":2361,"label":"40"},"type":"yellow card","text":"Bernardo Espinosa (Sporting de Gijón) is shown the yellow card for a bad foul.","playerIds":[19601]},{"id":649012,"time":{"secs":2355,"label":"40"},"type":"free kick won","text":"Jona (Real Jaén) wins a free kick on the left wing.","playerIds":[37256]},{"id":648944,"time":{"secs":2355,"label":"40"},"type":"free kick lost","text":"Foul by Bernardo Espinosa (Sporting de Gijón).","playerIds":[19601]},{"id":649032,"time":{"secs":2219,"label":"37"},"type":"goal","text":"Goal!  Real Jaén 1, Sporting de Gijón 1. Jona (Real Jaén) right footed shot from the right side of the six yard box to the bottom left corner. Assisted by Óscar Rico with a cross.","playerIds":[37256,37252]},{"id":649024,"time":{"secs":2023,"label":"34"},"type":"yellow card","text":"Luis Hernández (Sporting de Gijón) is shown the yellow card for a bad foul.","playerIds":[19599]},{"id":648943,"time":{"secs":2019,"label":"34"},"type":"free kick lost","text":"Foul by Luis Hernández (Sporting de Gijón).","playerIds":[19599]},{"id":648953,"time":{"secs":2019,"label":"34"},"type":"free kick won","text":"Óscar Rico (Real Jaén) wins a free kick in the attacking half.","playerIds":[37252]},{"id":649014,"time":{"secs":1998,"label":"34"},"type":"free kick lost","text":"Dangerous play by Carlos Carmona (Sporting de Gijón).","playerIds":[36226]},{"id":648922,"time":{"secs":1998,"label":"34"},"type":"free kick won","text":"José Cruz (Real Jaén) wins a free kick in the defensive half.","playerIds":[37243]},{"id":648977,"time":{"secs":1949,"label":"33"},"type":"attempt blocked","text":"Attempt blocked. Luis Hernández (Sporting de Gijón) right footed shot from the right side of the box is blocked.","playerIds":[19599]},{"id":648984,"time":{"secs":1860,"label":"32"},"type":"free kick won","text":"Fran Machado (Real Jaén) wins a free kick on the right wing.","playerIds":[37251]},{"id":649007,"time":{"secs":1860,"label":"32"},"type":"free kick lost","text":"Foul by Sergio Álvarez (Sporting de Gijón).","playerIds":[36088]},{"id":648934,"time":{"secs":1756,"label":"30"},"type":"miss","text":"Attempt missed. Jona (Real Jaén) right footed shot from outside the box is close, but misses to the right. Assisted by Juanma.","playerIds":[37256,37250]},{"id":648994,"time":{"secs":1591,"label":"27"},"type":"free kick won","text":"Sergio Álvarez (Sporting de Gijón) wins a free kick in the defensive half.","playerIds":[36088]},{"id":648924,"time":{"secs":1591,"label":"27"},"type":"free kick lost","text":"Foul by Fran Machado (Real Jaén).","playerIds":[37251]},{"id":649005,"time":{"secs":1575,"label":"27"},"type":"substitution","text":"Substitution, Real Jaén. Óscar Rico replaces Nino because of an injury.","playerIds":[37252,36206]},{"id":649000,"time":{"secs":1551,"label":"26"},"type":"free kick won","text":"Juanma (Real Jaén) wins a free kick in the defensive half.","playerIds":[37250]},{"id":649017,"time":{"secs":1551,"label":"26"},"type":"free kick lost","text":"Foul by Carlos Carmona (Sporting de Gijón).","playerIds":[36226]},{"id":648974,"time":{"secs":1445,"label":"25"},"type":"free kick lost","text":"Foul by Juanma (Real Jaén).","playerIds":[37250]},{"id":649003,"time":{"secs":1445,"label":"25"},"type":"free kick won","text":"Carlos Carmona (Sporting de Gijón) wins a free kick in the defensive half.","playerIds":[36226]},{"id":649031,"time":{"secs":1437,"label":"24"},"type":"substitution","text":"Substitution, Sporting de Gijón. Formose Mendy replaces Álex Barrera because of an injury.","playerIds":[10581,37097]},{"id":649030,"time":{"secs":1334,"label":"23"},"type":"miss","text":"Attempt missed. Jozabed Sánchez (Real Jaén) right footed shot from outside the box is high and wide to the right. Assisted by José Cruz.","playerIds":[19861,37243]},{"id":648923,"time":{"secs":1246,"label":"21"},"type":"end delay","text":"Delay over. They are ready to continue."},{"id":648985,"time":{"secs":1212,"label":"21"},"type":"start delay","text":"Delay in match Álex Barrera (Sporting de Gijón) because of an injury."},{"id":648926,"time":{"secs":1132,"label":"19"},"type":"free kick lost","text":"Foul by Sergio Álvarez (Sporting de Gijón).","playerIds":[36088]},{"id":648945,"time":{"secs":1132,"label":"19"},"type":"free kick won","text":"Jozabed Sánchez (Real Jaén) wins a free kick on the right wing.","playerIds":[19861]},{"id":649022,"time":{"secs":1050,"label":"18"},"type":"free kick won","text":"Jona (Real Jaén) wins a free kick on the right wing.","playerIds":[37256]},{"id":648955,"time":{"secs":1050,"label":"18"},"type":"free kick lost","text":"Foul by Roberto Canella (Sporting de Gijón).","playerIds":[36081]},{"id":648917,"time":{"secs":896,"label":"15"},"type":"miss","text":"Attempt missed. Bernardo Espinosa (Sporting de Gijón) header from the centre of the box misses to the right. Assisted by Nacho Cases with a cross following a corner.","playerIds":[19601,36090]},{"id":649033,"time":{"secs":860,"label":"15"},"type":"corner","text":"Corner,  Sporting de Gijón. Conceded by Óscar Quesada.","playerIds":[37253]},{"id":648960,"time":{"secs":856,"label":"15"},"type":"attempt blocked","text":"Attempt blocked. Luis Hernández (Sporting de Gijón) left footed shot from outside the box is blocked.","playerIds":[19599]},{"id":648996,"time":{"secs":795,"label":"14"},"type":"attempt saved","text":"Attempt saved. Roberto Canella (Sporting de Gijón) left footed shot from the centre of the box is saved in the centre of the goal. Assisted by Stefan Scepovic.","playerIds":[36081,12190]},{"id":649015,"time":{"secs":754,"label":"13"},"type":"free kick won","text":"Carlos Carmona (Sporting de Gijón) wins a free kick in the defensive half.","playerIds":[36226]},{"id":648925,"time":{"secs":754,"label":"13"},"type":"free kick lost","text":"Foul by Óscar Quesada (Real Jaén).","playerIds":[37253]},{"id":649018,"time":{"secs":748,"label":"13"},"type":"free kick lost","text":"Foul by Luis Hernández (Sporting de Gijón).","playerIds":[19599]},{"id":649034,"time":{"secs":748,"label":"13"},"type":"free kick won","text":"Fran Machado (Real Jaén) wins a free kick on the left wing.","playerIds":[37251]},{"id":648961,"time":{"secs":717,"label":"12"},"type":"free kick lost","text":"Foul by Carlos Carmona (Sporting de Gijón).","playerIds":[36226]},{"id":648992,"time":{"secs":717,"label":"12"},"type":"free kick won","text":"Nino (Real Jaén) wins a free kick in the defensive half.","playerIds":[36206]},{"id":648941,"time":{"secs":615,"label":"11"},"type":"corner","text":"Corner,  Real Jaén. Conceded by Roberto Canella.","playerIds":[36081]},{"id":648993,"time":{"secs":566,"label":"10"},"type":"offside","text":"Offside, Sporting de Gijón. Álex Barrera tries a through ball, but Alberto Lora is caught offside.","playerIds":[37097]},{"id":649016,"time":{"secs":518,"label":"09"},"type":"free kick won","text":"Israel Jerez (Real Jaén) wins a free kick on the right wing.","playerIds":[39095]},{"id":648932,"time":{"secs":518,"label":"09"},"type":"free kick lost","text":"Foul by Roberto Canella (Sporting de Gijón).","playerIds":[36081]},{"id":648946,"time":{"secs":76,"label":"02"},"type":"goal","text":"Goal!  Real Jaén 0, Sporting de Gijón 1. Stefan Scepovic (Sporting de Gijón) left footed shot from very close range to the centre of the goal. Assisted by Álex Barrera.","playerIds":[12190,37097]},{"id":648928,"time":{"secs":0,"label":"01"},"type":"start","text":"First Half begins."},{"id":648935,"type":"lineup","text":"Lineups are announced and players are warming up."}]}}