{"fixture":{"gameweek":{"id":2744,"gameweek":38},"kickoff":{"completeness":3,"millis":1370113200000,"label":"Sat 1 Jun 2013, 20:00 BST","gmtOffset":1.0},"provisionalKickoff":{"completeness":3,"millis":1370113200000,"label":"Sat 1 Jun 2013, 20:00 BST","gmtOffset":1.0},"teams":[{"team":{"name":"Mallorca","club":{"name":"Mallorca","abbr":"MLL","id":618},"teamType":"FIRST","shortName":"Mallorca","id":759},"score":4},{"team":{"name":"Real Valladolid","club":{"name":"Real Valladolid","abbr":"VLD","id":634},"teamType":"FIRST","shortName":"Valladolid","id":776},"score":2}],"replay":false,"ground":{"name":"Iberostar Estadi","city":"Palma de Mallorca","id":1401},"status":"C","phase":"F","outcome":"H","attendance":15000,"clock":{"secs":5700,"label":"90 +5\u002700"},"fixtureType":"REGULAR","extraTime":false,"shootout":false,"id":34244},"events":{"pageInfo":{"page":0,"numPages":1,"pageSize":1000,"numEntries":100},"content":[{"id":915607,"time":{"secs":0,"label":"01"},"type":"end 14","text":"Match ends, Mallorca 4, Real Valladolid 2."},{"id":915634,"time":{"secs":5643,"label":"90 +5"},"type":"end 2","text":"Second Half ends, Mallorca 4, Real Valladolid 2."},{"id":915626,"time":{"secs":5581,"label":"90 +4"},"type":"corner","text":"Corner,  Mallorca. Conceded by Antonio Rukavina.","playerIds":[12936]},{"id":915641,"time":{"secs":5577,"label":"90 +3"},"type":"attempt saved","text":"Attempt saved. Nsue (Mallorca) right footed shot from the right side of the box is saved in the bottom left corner. Assisted by Víctor Casadesús.","playerIds":[10800,35975]},{"id":915614,"time":{"secs":5505,"label":"90 +2"},"type":"attempt saved","text":"Attempt saved. Jesús Rueda (Real Valladolid) right footed shot from outside the box is saved in the centre of the goal.","playerIds":[24844]},{"id":915622,"time":{"secs":5474,"label":"90 +2"},"type":"corner","text":"Corner,  Real Valladolid. Conceded by Pedro Bigas.","playerIds":[37215]},{"id":915635,"time":{"secs":5405,"label":"90 +1"},"type":"miss","text":"Attempt missed. Lolo Plá (Real Valladolid) right footed shot from outside the box is close, but misses to the left. Assisted by Daniel Larsson.","playerIds":[19553,37970]},{"id":915585,"time":{"secs":5320,"label":"89"},"type":"substitution","text":"Substitution, Mallorca. Tomás Pina replaces Martí.","playerIds":[12940,35971]},{"id":915572,"time":{"secs":5275,"label":"88"},"type":"miss","text":"Attempt missed. Lolo Plá (Real Valladolid) right footed shot from outside the box is close, but misses the top left corner. Assisted by Omar Ramos.","playerIds":[19553,26080]},{"id":915628,"time":{"secs":5168,"label":"87"},"type":"attempt saved","text":"Attempt saved. Pedro Bigas (Mallorca) left footed shot from outside the box is saved in the centre of the goal.","playerIds":[37215]},{"id":915581,"time":{"secs":5027,"label":"84"},"type":"substitution","text":"Substitution, Mallorca. Michael Pereira replaces Alejandro Alfaro.","playerIds":[35974,36072]},{"id":915550,"time":{"secs":4985,"label":"84"},"type":"corner","text":"Corner,  Mallorca. Conceded by Carlos Peña.","playerIds":[26411]},{"id":915566,"time":{"secs":4882,"label":"82"},"type":"free kick lost","text":"Foul by Javier Baraja (Real Valladolid).","playerIds":[36543]},{"id":915627,"time":{"secs":4882,"label":"82"},"type":"free kick won","text":"Víctor Casadesús (Mallorca) wins a free kick on the left wing.","playerIds":[35975]},{"id":915563,"time":{"secs":4753,"label":"80"},"type":"yellow card","text":"Javi Márquez (Mallorca) is shown the yellow card for a bad foul.","playerIds":[32760]},{"id":915590,"time":{"secs":4746,"label":"80"},"type":"free kick lost","text":"Foul by Javi Márquez (Mallorca).","playerIds":[32760]},{"id":915620,"time":{"secs":4746,"label":"80"},"type":"free kick won","text":"Valdet Rama (Real Valladolid) wins a free kick on the right wing.","playerIds":[37968]},{"id":915574,"time":{"secs":4698,"label":"79"},"type":"free kick lost","text":"Foul by Lolo Plá (Real Valladolid).","playerIds":[19553]},{"id":915640,"time":{"secs":4698,"label":"79"},"type":"free kick won","text":"Javi Márquez (Mallorca) wins a free kick in the attacking half.","playerIds":[32760]},{"id":915553,"time":{"secs":4655,"label":"78"},"type":"free kick lost","text":"Foul by Carlos Peña (Real Valladolid).","playerIds":[26411]},{"id":915568,"time":{"secs":4655,"label":"78"},"type":"free kick won","text":"Nsue (Mallorca) wins a free kick in the defensive half.","playerIds":[10800]},{"id":915569,"time":{"secs":4562,"label":"77"},"type":"free kick lost","text":"Foul by Víctor Pérez (Real Valladolid).","playerIds":[36400]},{"id":915592,"time":{"secs":4562,"label":"77"},"type":"free kick won","text":"Javi Márquez (Mallorca) wins a free kick on the left wing.","playerIds":[32760]},{"id":915584,"time":{"secs":4509,"label":"76"},"type":"substitution","text":"Substitution, Real Valladolid. Valdet Rama replaces Patrick Ebert.","playerIds":[37968,34784]},{"id":915598,"time":{"secs":4494,"label":"75"},"type":"substitution","text":"Substitution, Mallorca. Nsue replaces Giovani dos Santos.","playerIds":[10800,3729]},{"id":915616,"time":{"secs":4455,"label":"75"},"type":"attempt blocked","text":"Attempt blocked. Javi Márquez (Mallorca) left footed shot from outside the box is blocked.","playerIds":[32760]},{"id":915609,"time":{"secs":4419,"label":"74"},"type":"free kick lost","text":"Foul by Daniel Larsson (Real Valladolid).","playerIds":[37970]},{"id":915639,"time":{"secs":4419,"label":"74"},"type":"free kick won","text":"Geromel (Mallorca) wins a free kick in the defensive half.","playerIds":[37337]},{"id":915600,"time":{"secs":4368,"label":"73"},"type":"offside","text":"Offside, Real Valladolid. Omar Ramos tries a through ball, but Carlos Peña is caught offside.","playerIds":[26080]},{"id":915558,"time":{"secs":4347,"label":"73"},"type":"free kick lost","text":"Foul by Alan Hutton (Mallorca).","playerIds":[3506]},{"id":915624,"time":{"secs":4347,"label":"73"},"type":"free kick won","text":"Omar Ramos (Real Valladolid) wins a free kick in the attacking half.","playerIds":[26080]},{"id":915576,"time":{"secs":4321,"label":"73"},"type":"free kick won","text":"Jesús Rueda (Real Valladolid) wins a free kick in the defensive half.","playerIds":[24844]},{"id":915580,"time":{"secs":4321,"label":"73"},"type":"free kick lost","text":"Foul by Javi Márquez (Mallorca).","playerIds":[32760]},{"id":915593,"time":{"secs":4284,"label":"72"},"type":"substitution","text":"Substitution, Real Valladolid. Lolo Plá replaces Alberto Bueno.","playerIds":[19553,15725]},{"id":915602,"time":{"secs":4260,"label":"72"},"type":"goal","text":"Goal!  Mallorca 4, Real Valladolid 2. Omar Ramos (Real Valladolid) left footed shot from the centre of the box to the bottom left corner. Assisted by Alberto Bueno with a cross.","playerIds":[26080,15725]},{"id":915605,"time":{"secs":4214,"label":"71"},"type":"attempt saved","text":"Attempt saved. Martí (Mallorca) right footed shot from outside the box is saved in the bottom left corner. Assisted by Víctor Casadesús.","playerIds":[35971,35975]},{"id":915562,"time":{"secs":4067,"label":"68"},"type":"goal","text":"Goal!  Mallorca 4, Real Valladolid 1. Javi Márquez (Mallorca) left footed shot from outside the box to the bottom right corner. Assisted by Víctor Casadesús.","playerIds":[32760,35975]},{"id":915621,"time":{"secs":4008,"label":"67"},"type":"corner","text":"Corner,  Real Valladolid. Conceded by Antonio Luna.","playerIds":[4720]},{"id":915570,"time":{"secs":3974,"label":"67"},"type":"substitution","text":"Substitution, Real Valladolid. Javier Baraja replaces Álvaro Rubio.","playerIds":[36543,36549]},{"id":915630,"time":{"secs":3945,"label":"66"},"type":"corner","text":"Corner,  Real Valladolid. Conceded by Antonio Luna.","playerIds":[4720]},{"id":915638,"time":{"secs":3738,"label":"63"},"type":"miss","text":"Attempt missed. Álvaro Rubio (Real Valladolid) right footed shot from outside the box misses to the right.","playerIds":[36549]},{"id":915571,"time":{"secs":3645,"label":"61"},"type":"free kick lost","text":"Foul by Víctor Pérez (Real Valladolid).","playerIds":[36400]},{"id":915601,"time":{"secs":3645,"label":"61"},"type":"free kick won","text":"Antonio Luna (Mallorca) wins a free kick in the attacking half.","playerIds":[4720]},{"id":915613,"time":{"secs":3449,"label":"58"},"type":"goal","text":"Goal!  Mallorca 3, Real Valladolid 1. Giovani dos Santos (Mallorca) left footed shot from outside the box to the bottom right corner. Assisted by Javi Márquez.","playerIds":[3729,32760]},{"id":915604,"time":{"secs":3049,"label":"51"},"type":"miss","text":"Attempt missed. Alberto Bueno (Real Valladolid) right footed shot from outside the box is just a bit too high from a direct free kick.","playerIds":[15725]},{"id":915648,"time":{"secs":2968,"label":"50"},"type":"yellow card","text":"Geromel (Mallorca) is shown the yellow card for a bad foul.","playerIds":[37337]},{"id":915606,"time":{"secs":2945,"label":"50"},"type":"free kick lost","text":"Foul by Geromel (Mallorca).","playerIds":[37337]},{"id":915643,"time":{"secs":2945,"label":"50"},"type":"free kick won","text":"Daniel Larsson (Real Valladolid) wins a free kick in the attacking half.","playerIds":[37970]},{"id":915623,"time":{"secs":2794,"label":"47"},"type":"corner","text":"Corner,  Real Valladolid. Conceded by Dudu Aouate.","playerIds":[35957]},{"id":915596,"time":{"secs":2793,"label":"47"},"type":"attempt saved","text":"Attempt saved. Omar Ramos (Real Valladolid) right footed shot from the centre of the box is saved in the bottom right corner. Assisted by Alberto Bueno.","playerIds":[26080,15725]},{"id":915594,"time":{"secs":2700,"label":"46"},"type":"start","text":"Second Half begins Mallorca 2, Real Valladolid 1."},{"id":915588,"time":{"secs":2702,"label":"45 +1"},"type":"end 1","text":"First Half ends, Mallorca 2, Real Valladolid 1."},{"id":915586,"time":{"secs":2540,"label":"43"},"type":"goal","text":"Goal!  Mallorca 2, Real Valladolid 1. Martí (Mallorca) right footed shot from outside the box to the bottom right corner.","playerIds":[35971]},{"id":915554,"time":{"secs":2470,"label":"42"},"type":"free kick lost","text":"Foul by Martí (Mallorca).","playerIds":[35971]},{"id":915636,"time":{"secs":2470,"label":"42"},"type":"free kick won","text":"Patrick Ebert (Real Valladolid) wins a free kick in the defensive half.","playerIds":[34784]},{"id":915555,"time":{"secs":2396,"label":"40"},"type":"free kick won","text":"Patrick Ebert (Real Valladolid) wins a free kick on the right wing.","playerIds":[34784]},{"id":915629,"time":{"secs":2396,"label":"40"},"type":"free kick lost","text":"Foul by Antonio Luna (Mallorca).","playerIds":[4720]},{"id":915559,"time":{"secs":2300,"label":"39"},"type":"corner","text":"Corner,  Mallorca. Conceded by Antonio Rukavina.","playerIds":[12936]},{"id":915617,"time":{"secs":2223,"label":"38"},"type":"miss","text":"Attempt missed. Daniel Larsson (Real Valladolid) header from the centre of the box misses to the right. Assisted by Víctor Pérez with a through ball.","playerIds":[37970,36400]},{"id":915597,"time":{"secs":2089,"label":"35"},"type":"attempt saved","text":"Attempt saved. Víctor Casadesús (Mallorca) header from the centre of the box is saved in the centre of the goal. Assisted by Alan Hutton with a cross.","playerIds":[35975,3506]},{"id":915599,"time":{"secs":2037,"label":"34"},"type":"free kick lost","text":"Dangerous play by Patrick Ebert (Real Valladolid).","playerIds":[34784]},{"id":915610,"time":{"secs":2037,"label":"34"},"type":"free kick won","text":"Antonio Luna (Mallorca) wins a free kick on the left wing.","playerIds":[4720]},{"id":915556,"time":{"secs":2018,"label":"34"},"type":"miss","text":"Attempt missed. Martí (Mallorca) left footed shot from outside the box is close, but misses to the left. Assisted by Geromel.","playerIds":[35971,37337]},{"id":915591,"time":{"secs":2016,"label":"34"},"type":"attempt blocked","text":"Attempt blocked. Geromel (Mallorca) right footed shot from outside the box is blocked.","playerIds":[37337]},{"id":915632,"time":{"secs":1995,"label":"34"},"type":"miss","text":"Attempt missed. Alejandro Alfaro (Mallorca) header from very close range misses to the right. Assisted by Javi Márquez with a cross following a corner.","playerIds":[36072,32760]},{"id":915608,"time":{"secs":1979,"label":"33"},"type":"corner","text":"Corner,  Mallorca. Conceded by Jaime.","playerIds":[36295]},{"id":915561,"time":{"secs":1977,"label":"33"},"type":"attempt saved","text":"Attempt saved. Víctor Casadesús (Mallorca) header from the centre of the box is saved in the top left corner. Assisted by Javi Márquez with a cross.","playerIds":[35975,32760]},{"id":915603,"time":{"secs":1951,"label":"33"},"type":"corner","text":"Corner,  Mallorca. Conceded by Jaime.","playerIds":[36295]},{"id":915549,"time":{"secs":1950,"label":"33"},"type":"attempt saved","text":"Attempt saved. Pedro Bigas (Mallorca) right footed shot from the centre of the box is saved in the top centre of the goal. Assisted by Martí with a cross.","playerIds":[37215,35971]},{"id":915577,"time":{"secs":1900,"label":"32"},"type":"corner","text":"Corner,  Mallorca. Conceded by Jaime.","playerIds":[36295]},{"id":915612,"time":{"secs":1898,"label":"32"},"type":"miss","text":"Attempt missed. Giovani dos Santos (Mallorca) left footed shot from a difficult angle on the right is close, but misses to the right. Assisted by Alejandro Alfaro.","playerIds":[3729,36072]},{"id":915564,"time":{"secs":1778,"label":"30"},"type":"goal","text":"Goal!  Mallorca 1, Real Valladolid 1. Alberto Bueno (Real Valladolid) left footed shot from the left side of the six yard box to the centre of the goal.","playerIds":[15725]},{"id":915647,"time":{"secs":1776,"label":"30"},"type":"attempt saved","text":"Attempt saved. Omar Ramos (Real Valladolid) right footed shot from the left side of the box is saved in the centre of the goal. Assisted by Patrick Ebert.","playerIds":[26080,34784]},{"id":915551,"time":{"secs":1716,"label":"29"},"type":"corner","text":"Corner,  Mallorca. Conceded by Marc Valiente.","playerIds":[36539]},{"id":915587,"time":{"secs":1610,"label":"27"},"type":"miss","text":"Attempt missed. Giovani dos Santos (Mallorca) left footed shot from the left side of the box is just a bit too high. Assisted by Víctor Casadesús with a through ball following a fast break.","playerIds":[3729,35975]},{"id":915595,"time":{"secs":1488,"label":"25"},"type":"offside","text":"Offside, Real Valladolid. Daniel Larsson tries a through ball, but Omar Ramos is caught offside.","playerIds":[37970]},{"id":915575,"time":{"secs":1419,"label":"24"},"type":"free kick lost","text":"Foul by Carlos Peña (Real Valladolid).","playerIds":[26411]},{"id":915618,"time":{"secs":1419,"label":"24"},"type":"free kick won","text":"Giovani dos Santos (Mallorca) wins a free kick on the right wing.","playerIds":[3729]},{"id":915565,"time":{"secs":1334,"label":"23"},"type":"free kick lost","text":"Foul by Martí (Mallorca).","playerIds":[35971]},{"id":915645,"time":{"secs":1334,"label":"23"},"type":"free kick won","text":"Daniel Larsson (Real Valladolid) wins a free kick in the attacking half.","playerIds":[37970]},{"id":915633,"time":{"secs":1320,"label":"23"},"type":"miss","text":"Attempt missed. Martí (Mallorca) left footed shot from the centre of the box misses to the left. Assisted by Alan Hutton.","playerIds":[35971,3506]},{"id":915578,"time":{"secs":1193,"label":"20"},"type":"miss","text":"Attempt missed. Omar Ramos (Real Valladolid) left footed shot from outside the box is just a bit too high. Assisted by Daniel Larsson.","playerIds":[26080,37970]},{"id":915567,"time":{"secs":1093,"label":"19"},"type":"corner","text":"Corner,  Real Valladolid. Conceded by Martí.","playerIds":[35971]},{"id":915583,"time":{"secs":984,"label":"17"},"type":"goal","text":"Goal!  Mallorca 1, Real Valladolid 0. Alejandro Alfaro (Mallorca) right footed shot from the centre of the box to the centre of the goal. Assisted by Víctor Casadesús with a through ball.","playerIds":[36072,35975]},{"id":915619,"time":{"secs":969,"label":"17"},"type":"free kick won","text":"Pedro Bigas (Mallorca) wins a free kick in the defensive half.","playerIds":[37215]},{"id":915625,"time":{"secs":969,"label":"17"},"type":"free kick lost","text":"Foul by Daniel Larsson (Real Valladolid).","playerIds":[37970]},{"id":915557,"time":{"secs":936,"label":"16"},"type":"free kick lost","text":"Foul by Daniel Larsson (Real Valladolid).","playerIds":[37970]},{"id":915644,"time":{"secs":936,"label":"16"},"type":"free kick won","text":"Pedro Bigas (Mallorca) wins a free kick in the defensive half.","playerIds":[37215]},{"id":915589,"time":{"secs":900,"label":"16"},"type":"free kick won","text":"Álvaro Rubio (Real Valladolid) wins a free kick in the defensive half.","playerIds":[36549]},{"id":915611,"time":{"secs":900,"label":"16"},"type":"free kick lost","text":"Foul by Martí (Mallorca).","playerIds":[35971]},{"id":915552,"time":{"secs":881,"label":"15"},"type":"miss","text":"Attempt missed. Javi Márquez (Mallorca) left footed shot from long range on the left is just a bit too high. Assisted by Antonio Luna.","playerIds":[32760,4720]},{"id":915646,"time":{"secs":776,"label":"13"},"type":"corner","text":"Corner,  Mallorca. Conceded by Carlos Peña.","playerIds":[26411]},{"id":915579,"time":{"secs":570,"label":"10"},"type":"free kick lost","text":"Foul by Antonio Rukavina (Real Valladolid).","playerIds":[12936]},{"id":915582,"time":{"secs":570,"label":"10"},"type":"free kick won","text":"Alejandro Alfaro (Mallorca) wins a free kick on the left wing.","playerIds":[36072]},{"id":915642,"time":{"secs":418,"label":"07"},"type":"miss","text":"Attempt missed. Víctor Casadesús (Mallorca) header from the centre of the box misses to the left. Assisted by Martí.","playerIds":[35975,35971]},{"id":915631,"time":{"secs":201,"label":"04"},"type":"miss","text":"Attempt missed. Alan Hutton (Mallorca) header from the centre of the box misses to the left. Assisted by Martí with a cross following a corner.","playerIds":[3506,35971]},{"id":915637,"time":{"secs":176,"label":"03"},"type":"corner","text":"Corner,  Mallorca. Conceded by Omar Ramos.","playerIds":[26080]},{"id":915560,"time":{"secs":23,"label":"01"},"type":"miss","text":"Attempt missed. Alejandro Alfaro (Mallorca) right footed shot from outside the box is too high. Assisted by Antonio Luna.","playerIds":[36072,4720]},{"id":915615,"time":{"secs":0,"label":"01"},"type":"start","text":"First Half begins."},{"id":915573,"type":"lineup","text":"Lineups are announced and players are warming up."}]}}