{"fixture":{"gameweek":{"id":830,"gameweek":4},"kickoff":{"completeness":3,"millis":1383854700000,"label":"Thu 7 Nov 2013, 20:05 GMT"},"provisionalKickoff":{"completeness":0},"teams":[{"team":{"name":"Maccabi Haifa","club":{"name":"Maccabi Haifa","abbr":"MHI","id":99},"teamType":"FIRST","shortName":"Maccabi Haifa","id":99},"score":0},{"team":{"name":"PAOK Salonika","club":{"name":"PAOK Salonika","abbr":"PAO","id":104},"teamType":"FIRST","shortName":"PAOK Salonika","id":104},"score":0}],"replay":false,"ground":{"name":"Kiryat Eliezer","city":"Haifa","id":329},"neutralGround":false,"status":"C","phase":"F","outcome":"D","clock":{"secs":5760,"label":"90 +6\u002700"},"group":"L","fixtureType":"REGULAR","extraTime":false,"shootout":false,"id":8417},"events":{"pageInfo":{"page":0,"numPages":0,"pageSize":1000,"numEntries":0},"content":[]}}